{
  "version": 1,
  "base_track": "P-O-P-T-R-A-I-N",
  "base_artist": "ノーナ・リーヴス",
  "createdAt": "2026-02-12T10:31:44.214308Z",
  "candidates": [
    {
      "id": "lrclib_1",
      "source": "lrclib",
      "title": "P-O-P-T-R-A-I-N",
      "artist": "NONA REEVES",
      "has_synced": true,
      "path": "select/01_P-O-P-T-R-A-I-N_NONA_REEVES.lrc"
    },
    {
      "id": "petitlyrics_1",
      "source": "petitlyrics",
      "title": "P-O-P-T-R-A-I-N",
      "artist": "Nona Reeves",
      "has_synced": false,
      "path": "select/pl_01_P-O-P-T-R-A-I-N_Nona_Reeves.txt"
    }
  ]
}